inginious_coding_style/__init__.py
inginious_coding_style/_types.py
inginious_coding_style/config.py
inginious_coding_style/exceptions.py
inginious_coding_style/fs.py
inginious_coding_style/grades.py
inginious_coding_style/logger.py
inginious_coding_style/mixins.py
inginious_coding_style/pages/__init__.py
inginious_coding_style/pages/base.py
inginious_coding_style/pages/grade_student.py
inginious_coding_style/pages/grade_tutor.py
inginious_coding_style/pages/plugin_settings.py
inginious_coding_style/submission.py
inginious_coding_style/templates/alert.html
inginious_coding_style/templates/diagnosis.html
inginious_coding_style/templates/grade_submission.html
inginious_coding_style/templates/newcategory.html
inginious_coding_style/templates/plugin_settings.html
inginious_coding_style/templates/recalculate_grades.html
inginious_coding_style/templates/repair_submissions.html
inginious_coding_style/templates/stylegrade.html
inginious_coding_style/templates/submission_admin_menu.html
inginious_coding_style/templates/submission_query_button.html
inginious_coding_style/templates/submission_query_cell.html
inginious_coding_style/templates/submission_query_header.html
inginious_coding_style/templates/task_list_item.html
inginious_coding_style/templates/task_menu.html
inginious_coding_style/utils.py
inginious_coding_style-1.5.3.dist-info/LICENSE
inginious_coding_style-1.5.3.dist-info/WHEEL
inginious_coding_style-1.5.3.dist-info/METADATA
inginious_coding_style-1.5.3.dist-info/RECORD
