Metadata-Version: 2.1
Name: inginious-coding-style
Version: 1.5.3
Summary: INGInious plugin for grading of coding style.
Home-page: https://github.com/PederHA/inginious-coding-style
License: AGPL-3.0-or-later
Author: Peder Hovdan Andresen
Author-email: pedeha@stud.ntnu.no
Requires-Python: >=3.8,<4.0
Classifier: License :: OSI Approved :: GNU Affero General Public License v3 or later (AGPLv3+)
Classifier: Programming Language :: Python :: 3
Classifier: Programming Language :: Python :: 3.8
Classifier: Programming Language :: Python :: 3.9
Classifier: Topic :: Education
Classifier: Typing :: Typed
Requires-Dist: inginious (>=0.7,<0.8)
Requires-Dist: pydantic (>=1.8.2,<2.0.0)
Requires-Dist: unidecode (>=1.2.0,<2.0.0)
Project-URL: Documentation, https://pederha.github.io/inginious-coding-style
Project-URL: Repository, https://github.com/PederHA/inginious-coding-style
